flowpy/__init__.py
flowpy/flow_io.py
flowpy/flowpy.py
flowpy-0.6.0.data/scripts/flowread
flowpy-0.6.0.dist-info/LICENSE
flowpy-0.6.0.dist-info/METADATA
flowpy-0.6.0.dist-info/WHEEL
flowpy-0.6.0.dist-info/top_level.txt
flowpy-0.6.0.dist-info/RECORD
