Metadata-Version: 2.1
Name: flowpy
Version: 0.6.0
Summary: Tools for working with optical flow
Home-page: https://gitlab-research.centralesupelec.fr/2018seznecm/flowpy
Author: Mickaël Seznec
Author-email: mickael.seznec@centralesupelec.fr
License: MIT
Platform: UNKNOWN
Requires-Dist: matplotlib
Requires-Dist: numpy
Requires-Dist: pypng
Requires-Dist: scipy
